setup.cfg
setup.py
retrowait/__init__.py
retrowait/main.py
retrowait.egg-info/PKG-INFO
retrowait.egg-info/SOURCES.txt
retrowait.egg-info/dependency_links.txt
retrowait.egg-info/not-zip-safe
retrowait.egg-info/requires.txt
retrowait.egg-info/top_level.txt