Metadata-Version: 1.0
Name: retrowait
Version: 0.1
Summary: A Python adaptation of XKCD's 'Backward in Time'.
Home-page: https://github.com/rudimk/retrowait
Author: Rudraksh MK
Author-email: rudraksh.mk@gmail.com
License: MIT
Platform: UNKNOWN
